ocx_unitsml/__init__.py
ocx_unitsml/ocx_unitsml_0918/__init__.py
ocx_unitsml/ocx_unitsml_0918/ocx_unitsml_0918.py
ocx_unitsml/ocx_unitsml_0918/unitsml-v1.0-csd04.xsd
ocx_unitsml/ocx_unitsml_0918/xsdata.xml
ocx_unitsml/unitsmlSchema_lite.xsd
ocx_unitsml-0.9.18.dist-info/LICENSE
ocx_unitsml-0.9.18.dist-info/METADATA
ocx_unitsml-0.9.18.dist-info/WHEEL
ocx_unitsml-0.9.18.dist-info/RECORD
