Metadata-Version: 2.1
Name: ocx_unitsml
Version: 0.9.18
Summary: Python databinding for the Units Markup Language (UnitsML) lite schema
Author: ocastrup
Author-email: ole.christian.astrup@dnv.com
Requires-Python: >=3.11,<4.0
Classifier: Programming Language :: Python :: 3
Classifier: Programming Language :: Python :: 3.11
Requires-Dist: click
Requires-Dist: ocx_generator
Requires-Dist: packaging (>=23.1,<24.0)
Requires-Dist: tbump
Requires-Dist: xsdata (>=23.6,<24.0)
